neonunicorn/__init__.py
neonunicorn/_core.abi3.so
neonunicorn/_core.pyi
neonunicorn/py.typed
neonunicorn/differential/__init__.py
neonunicorn/differential/discrete.py
neonunicorn/distributions/__init__.py
neonunicorn/distributions/cvdistributions.py
neonunicorn/matrix/__init__.py
neonunicorn/matrix/elementary.py
neonunicorn/model/__init__.py
neonunicorn/model/regression.py
neonunicorn-0.1.9.dist-info/METADATA
neonunicorn-0.1.9.dist-info/WHEEL
neonunicorn-0.1.9.dist-info/RECORD
