Metadata-Version: 2.4
Name: neonunicorn
Version: 0.1.9
Requires-Dist: matplotlib>=3.9.4
Requires-Dist: numpy>=2.0.2
Requires-Dist: polars>=1.34.0
Requires-Dist: scikit-learn>=1.6.1
Requires-Dist: torch>=2.8.0
Requires-Dist: twine>=6.1.0
Summary: both package distribution and matrix
Author-email: neonunicorngh <fm0032@uah.edu>
Requires-Python: >=3.9
